[{"Start":"20251006T140000","End":"20251006T160000","StartDate":{"Year":"2025","Month":"10","Day":"06","Hour":"14","Minute":"00","Seconde":"00"},"EndDate":{"Year":"2025","Month":"10","Day":"06","Hour":"16","Minute":"00","Seconde":"00"},"Location":"202_Gouges (40p)","Summary":"Reactivity and organic synthesis"},{"Start":"20251007T090000","End":"20251007T120000","StartDate":{"Year":"2025","Month":"10","Day":"07","Hour":"09","Minute":"00","Seconde":"00"},"EndDate":{"Year":"2025","Month":"10","Day":"07","Hour":"12","Minute":"00","Seconde":"00"},"Location":"202_Gouges (40p),203_Gouges_40,265_Gouges_30,266_Gouges_30","Summary":"Anglais pour ingenieur 2eme annee TD01"},{"Start":"20251007T130000","End":"20251007T150000","StartDate":{"Year":"2025","Month":"10","Day":"07","Hour":"13","Minute":"00","Seconde":"00"},"EndDate":{"Year":"2025","Month":"10","Day":"07","Hour":"15","Minute":"00","Seconde":"00"},"Location":"202_Gouges (40p)","Summary":"MANAGEMENT PROJET GR 4"},{"Start":"20251007T151500","End":"20251007T181500","StartDate":{"Year":"2025","Month":"10","Day":"07","Hour":"15","Minute":"15","Seconde":"00"},"EndDate":{"Year":"2025","Month":"10","Day":"07","Hour":"18","Minute":"15","Seconde":"00"},"Location":"202_Gouges (40p)","Summary":"Animation d'equipe Gr 3"},{"Start":"20251008T083000","End":"20251008T100000","StartDate":{"Year":"2025","Month":"10","Day":"08","Hour":"08","Minute":"30","Seconde":"00"},"EndDate":{"Year":"2025","Month":"10","Day":"08","Hour":"10","Minute":"00","Seconde":"00"},"Location":"202_Gouges (40p)","Summary":"INFORMATIQUE FONDAMENTALE CM"},{"Start":"20251008T103000","End":"20251008T120000","StartDate":{"Year":"2025","Month":"10","Day":"08","Hour":"10","Minute":"30","Seconde":"00"},"EndDate":{"Year":"2025","Month":"10","Day":"08","Hour":"12","Minute":"00","Seconde":"00"},"Location":"202_Gouges (40p)","Summary":"INFORMATIQUE FONDAMENTALE CM"},{"Start":"20251008T120000","End":"20251008T140000","StartDate":{"Year":"2025","Month":"10","Day":"08","Hour":"12","Minute":"00","Seconde":"00"},"EndDate":{"Year":"2025","Month":"10","Day":"08","Hour":"14","Minute":"00","Seconde":"00"},"Location":"202_Gouges (40p)","Summary":"Scrabble"},{"Start":"20251008T140000","End":"20251008T170000","StartDate":{"Year":"2025","Month":"10","Day":"08","Hour":"14","Minute":"00","Seconde":"00"},"EndDate":{"Year":"2025","Month":"10","Day":"08","Hour":"17","Minute":"00","Seconde":"00"},"Location":"202_Gouges (40p),255_Gouges_60,203_Gouges_40,266_Gouges_30","Summary":"Anglais"},{"Start":"20251009T083000","End":"20251009T103000","StartDate":{"Year":"2025","Month":"10","Day":"09","Hour":"08","Minute":"30","Seconde":"00"},"EndDate":{"Year":"2025","Month":"10","Day":"09","Hour":"10","Minute":"30","Seconde":"00"},"Location":"202_Gouges (40p)","Summary":"Introduction à la théorie spectrale"},{"Start":"20251009T104500","End":"20251009T124500","StartDate":{"Year":"2025","Month":"10","Day":"09","Hour":"10","Minute":"45","Seconde":"00"},"EndDate":{"Year":"2025","Month":"10","Day":"09","Hour":"12","Minute":"45","Seconde":"00"},"Location":"202_Gouges (40p)","Summary":"Mathematiques 1 Gr B"},{"Start":"20251009T141500","End":"20251009T154500","StartDate":{"Year":"2025","Month":"10","Day":"09","Hour":"14","Minute":"15","Seconde":"00"},"EndDate":{"Year":"2025","Month":"10","Day":"09","Hour":"15","Minute":"45","Seconde":"00"},"Location":"202_Gouges (40p)","Summary":"La croissance economique : Faits et theories TD 02"},{"Start":"20251009T160000","End":"20251009T173000","StartDate":{"Year":"2025","Month":"10","Day":"09","Hour":"16","Minute":"00","Seconde":"00"},"EndDate":{"Year":"2025","Month":"10","Day":"09","Hour":"17","Minute":"30","Seconde":"00"},"Location":"202_Gouges (40p)","Summary":"La croissance economique : Faits et theories TD 01"},{"Start":"20251010T083000","End":"20251010T103000","StartDate":{"Year":"2025","Month":"10","Day":"10","Hour":"08","Minute":"30","Seconde":"00"},"EndDate":{"Year":"2025","Month":"10","Day":"10","Hour":"10","Minute":"30","Seconde":"00"},"Location":"202_Gouges (40p)","Summary":"MANAGEMENT PROJET CM"},{"Start":"20251010T124500","End":"20251010T134500","StartDate":{"Year":"2025","Month":"10","Day":"10","Hour":"12","Minute":"45","Seconde":"00"},"EndDate":{"Year":"2025","Month":"10","Day":"10","Hour":"13","Minute":"45","Seconde":"00"},"Location":"202_Gouges (40p)","Summary":"FRANCAIS 1A TD"},{"Start":"20251010T140000","End":"20251010T170000","StartDate":{"Year":"2025","Month":"10","Day":"10","Hour":"14","Minute":"00","Seconde":"00"},"EndDate":{"Year":"2025","Month":"10","Day":"10","Hour":"17","Minute":"00","Seconde":"00"},"Location":"202_Gouges (40p),265_Gouges_30,203_Gouges_40,266_Gouges_30","Summary":"Anglais pour ingenieur 1ere annee TD01"},{"Start":"20251013T083000","End":"20251013T103000","StartDate":{"Year":"2025","Month":"10","Day":"13","Hour":"08","Minute":"30","Seconde":"00"},"EndDate":{"Year":"2025","Month":"10","Day":"13","Hour":"10","Minute":"30","Seconde":"00"},"Location":"202_Gouges (40p)","Summary":"MANAGEMENT PROJET CM"},{"Start":"20251013T104500","End":"20251013T124500","StartDate":{"Year":"2025","Month":"10","Day":"13","Hour":"10","Minute":"45","Seconde":"00"},"EndDate":{"Year":"2025","Month":"10","Day":"13","Hour":"12","Minute":"45","Seconde":"00"},"Location":"202_Gouges (40p)","Summary":"Surfaces et interfaces TD01"},{"Start":"20251013T140000","End":"20251013T160000","StartDate":{"Year":"2025","Month":"10","Day":"13","Hour":"14","Minute":"00","Seconde":"00"},"EndDate":{"Year":"2025","Month":"10","Day":"13","Hour":"16","Minute":"00","Seconde":"00"},"Location":"202_Gouges (40p)","Summary":"Projet professionnel (FISE) - TD"},{"Start":"20251013T160000","End":"20251013T180000","StartDate":{"Year":"2025","Month":"10","Day":"13","Hour":"16","Minute":"00","Seconde":"00"},"EndDate":{"Year":"2025","Month":"10","Day":"13","Hour":"18","Minute":"00","Seconde":"00"},"Location":"202_Gouges (40p)","Summary":"Systemes de telecommunications 1 TD01"},{"Start":"20251014T090000","End":"20251014T120000","StartDate":{"Year":"2025","Month":"10","Day":"14","Hour":"09","Minute":"00","Seconde":"00"},"EndDate":{"Year":"2025","Month":"10","Day":"14","Hour":"12","Minute":"00","Seconde":"00"},"Location":"202_Gouges (40p),203_Gouges_40,265_Gouges_30,266_Gouges_30","Summary":"Anglais pour ingenieur 2eme annee TD01"},{"Start":"20251014T130000","End":"20251014T150000","StartDate":{"Year":"2025","Month":"10","Day":"14","Hour":"13","Minute":"00","Seconde":"00"},"EndDate":{"Year":"2025","Month":"10","Day":"14","Hour":"15","Minute":"00","Seconde":"00"},"Location":"202_Gouges (40p)","Summary":"Dispositifs Laser CM01"},{"Start":"20251014T151500","End":"20251014T181500","StartDate":{"Year":"2025","Month":"10","Day":"14","Hour":"15","Minute":"15","Seconde":"00"},"EndDate":{"Year":"2025","Month":"10","Day":"14","Hour":"18","Minute":"15","Seconde":"00"},"Location":"202_Gouges (40p)","Summary":"Animation d'equipe Gr 1"},{"Start":"20251015T080000","End":"20251015T100000","StartDate":{"Year":"2025","Month":"10","Day":"15","Hour":"08","Minute":"00","Seconde":"00"},"EndDate":{"Year":"2025","Month":"10","Day":"15","Hour":"10","Minute":"00","Seconde":"00"},"Location":"202_Gouges (40p)","Summary":"Programmation objets avancee CM01"},{"Start":"20251015T100000","End":"20251015T120000","StartDate":{"Year":"2025","Month":"10","Day":"15","Hour":"10","Minute":"00","Seconde":"00"},"EndDate":{"Year":"2025","Month":"10","Day":"15","Hour":"12","Minute":"00","Seconde":"00"},"Location":"202_Gouges (40p)","Summary":"Programmation objets avancee TP01"},{"Start":"20251015T120000","End":"20251015T140000","StartDate":{"Year":"2025","Month":"10","Day":"15","Hour":"12","Minute":"00","Seconde":"00"},"EndDate":{"Year":"2025","Month":"10","Day":"15","Hour":"14","Minute":"00","Seconde":"00"},"Location":"202_Gouges (40p)","Summary":"Scrabble"},{"Start":"20251015T140000","End":"20251015T170000","StartDate":{"Year":"2025","Month":"10","Day":"15","Hour":"14","Minute":"00","Seconde":"00"},"EndDate":{"Year":"2025","Month":"10","Day":"15","Hour":"17","Minute":"00","Seconde":"00"},"Location":"202_Gouges (40p),255_Gouges_60,203_Gouges_40,266_Gouges_30","Summary":"Anglais"},{"Start":"20251016T083000","End":"20251016T103000","StartDate":{"Year":"2025","Month":"10","Day":"16","Hour":"08","Minute":"30","Seconde":"00"},"EndDate":{"Year":"2025","Month":"10","Day":"16","Hour":"10","Minute":"30","Seconde":"00"},"Location":"202_Gouges (40p)","Summary":"Introduction à la théorie spectrale"},{"Start":"20251016T104500","End":"20251016T124500","StartDate":{"Year":"2025","Month":"10","Day":"16","Hour":"10","Minute":"45","Seconde":"00"},"EndDate":{"Year":"2025","Month":"10","Day":"16","Hour":"12","Minute":"45","Seconde":"00"},"Location":"202_Gouges (40p)","Summary":"Mathematiques 1 Gr B"},{"Start":"20251016T141500","End":"20251016T154500","StartDate":{"Year":"2025","Month":"10","Day":"16","Hour":"14","Minute":"15","Seconde":"00"},"EndDate":{"Year":"2025","Month":"10","Day":"16","Hour":"15","Minute":"45","Seconde":"00"},"Location":"202_Gouges (40p)","Summary":"La croissance economique : Faits et theories TD 02"},{"Start":"20251016T160000","End":"20251016T173000","StartDate":{"Year":"2025","Month":"10","Day":"16","Hour":"16","Minute":"00","Seconde":"00"},"EndDate":{"Year":"2025","Month":"10","Day":"16","Hour":"17","Minute":"30","Seconde":"00"},"Location":"202_Gouges (40p)","Summary":"La croissance economique : Faits et theories TD 01"},{"Start":"20251017T083000","End":"20251017T100000","StartDate":{"Year":"2025","Month":"10","Day":"17","Hour":"08","Minute":"30","Seconde":"00"},"EndDate":{"Year":"2025","Month":"10","Day":"17","Hour":"10","Minute":"00","Seconde":"00"},"Location":"202_Gouges (40p)","Summary":"Tech Repair TD03"},{"Start":"20251017T101500","End":"20251017T121500","StartDate":{"Year":"2025","Month":"10","Day":"17","Hour":"10","Minute":"15","Seconde":"00"},"EndDate":{"Year":"2025","Month":"10","Day":"17","Hour":"12","Minute":"15","Seconde":"00"},"Location":"202_Gouges (40p)","Summary":"ELECTRONIQUE 1 Gr C"},{"Start":"20251017T124500","End":"20251017T134500","StartDate":{"Year":"2025","Month":"10","Day":"17","Hour":"12","Minute":"45","Seconde":"00"},"EndDate":{"Year":"2025","Month":"10","Day":"17","Hour":"13","Minute":"45","Seconde":"00"},"Location":"202_Gouges (40p)","Summary":"FRANCAIS 1A TD"},{"Start":"20251017T140000","End":"20251017T170000","StartDate":{"Year":"2025","Month":"10","Day":"17","Hour":"14","Minute":"00","Seconde":"00"},"EndDate":{"Year":"2025","Month":"10","Day":"17","Hour":"17","Minute":"00","Seconde":"00"},"Location":"202_Gouges (40p),265_Gouges_30,203_Gouges_40,266_Gouges_30","Summary":"Anglais pour ingenieur 1ere annee TD01"},{"Start":"20251020T083000","End":"20251020T103000","StartDate":{"Year":"2025","Month":"10","Day":"20","Hour":"08","Minute":"30","Seconde":"00"},"EndDate":{"Year":"2025","Month":"10","Day":"20","Hour":"10","Minute":"30","Seconde":"00"},"Location":"202_Gouges (40p)","Summary":"Programmation objets avancee CM01"},{"Start":"20251020T104500","End":"20251020T124500","StartDate":{"Year":"2025","Month":"10","Day":"20","Hour":"10","Minute":"45","Seconde":"00"},"EndDate":{"Year":"2025","Month":"10","Day":"20","Hour":"12","Minute":"45","Seconde":"00"},"Location":"202_Gouges (40p)","Summary":"Surfaces et interfaces TD01"},{"Start":"20251020T134500","End":"20251020T154500","StartDate":{"Year":"2025","Month":"10","Day":"20","Hour":"13","Minute":"45","Seconde":"00"},"EndDate":{"Year":"2025","Month":"10","Day":"20","Hour":"15","Minute":"45","Seconde":"00"},"Location":"202_Gouges (40p)","Summary":"Techniques de caracterisation TD01 (RX)"},{"Start":"20251020T160000","End":"20251020T180000","StartDate":{"Year":"2025","Month":"10","Day":"20","Hour":"16","Minute":"00","Seconde":"00"},"EndDate":{"Year":"2025","Month":"10","Day":"20","Hour":"18","Minute":"00","Seconde":"00"},"Location":"202_Gouges (40p)","Summary":"Techniques de caracterisation TD01 (XPS)"},{"Start":"20251021T090000","End":"20251021T120000","StartDate":{"Year":"2025","Month":"10","Day":"21","Hour":"09","Minute":"00","Seconde":"00"},"EndDate":{"Year":"2025","Month":"10","Day":"21","Hour":"12","Minute":"00","Seconde":"00"},"Location":"202_Gouges (40p)","Summary":"Prepa. DELF / DALF TD01"},{"Start":"20251021T121500","End":"20251021T141500","StartDate":{"Year":"2025","Month":"10","Day":"21","Hour":"12","Minute":"15","Seconde":"00"},"EndDate":{"Year":"2025","Month":"10","Day":"21","Hour":"14","Minute":"15","Seconde":"00"},"Location":"202_Gouges (40p)","Summary":"créneau jeremy"},{"Start":"20251021T151500","End":"20251021T181500","StartDate":{"Year":"2025","Month":"10","Day":"21","Hour":"15","Minute":"15","Seconde":"00"},"EndDate":{"Year":"2025","Month":"10","Day":"21","Hour":"18","Minute":"15","Seconde":"00"},"Location":"202_Gouges (40p)","Summary":"Animation d'equipe Gr 3"},{"Start":"20251022T083000","End":"20251022T100000","StartDate":{"Year":"2025","Month":"10","Day":"22","Hour":"08","Minute":"30","Seconde":"00"},"EndDate":{"Year":"2025","Month":"10","Day":"22","Hour":"10","Minute":"00","Seconde":"00"},"Location":"202_Gouges (40p)","Summary":"INFORMATIQUE FONDAMENTALE CM"},{"Start":"20251022T103000","End":"20251022T120000","StartDate":{"Year":"2025","Month":"10","Day":"22","Hour":"10","Minute":"30","Seconde":"00"},"EndDate":{"Year":"2025","Month":"10","Day":"22","Hour":"12","Minute":"00","Seconde":"00"},"Location":"202_Gouges (40p)","Summary":"INFORMATIQUE FONDAMENTALE CM"},{"Start":"20251022T140000","End":"20251022T170000","StartDate":{"Year":"2025","Month":"10","Day":"22","Hour":"14","Minute":"00","Seconde":"00"},"EndDate":{"Year":"2025","Month":"10","Day":"22","Hour":"17","Minute":"00","Seconde":"00"},"Location":"202_Gouges (40p)","Summary":"Anglais"},{"Start":"20251023T100000","End":"20251023T130000","StartDate":{"Year":"2025","Month":"10","Day":"23","Hour":"10","Minute":"00","Seconde":"00"},"EndDate":{"Year":"2025","Month":"10","Day":"23","Hour":"13","Minute":"00","Seconde":"00"},"Location":"202_Gouges (40p)","Summary":"Techniques de releves de terrain et analyses en laboratoire TD01"},{"Start":"20251023T141500","End":"20251023T154500","StartDate":{"Year":"2025","Month":"10","Day":"23","Hour":"14","Minute":"15","Seconde":"00"},"EndDate":{"Year":"2025","Month":"10","Day":"23","Hour":"15","Minute":"45","Seconde":"00"},"Location":"202_Gouges (40p)","Summary":"La croissance economique : Faits et theories TD 02"},{"Start":"20251023T160000","End":"20251023T173000","StartDate":{"Year":"2025","Month":"10","Day":"23","Hour":"16","Minute":"00","Seconde":"00"},"EndDate":{"Year":"2025","Month":"10","Day":"23","Hour":"17","Minute":"30","Seconde":"00"},"Location":"202_Gouges (40p)","Summary":"La croissance economique : Faits et theories TD 01"},{"Start":"20251024T090000","End":"20251024T103000","StartDate":{"Year":"2025","Month":"10","Day":"24","Hour":"09","Minute":"00","Seconde":"00"},"EndDate":{"Year":"2025","Month":"10","Day":"24","Hour":"10","Minute":"30","Seconde":"00"},"Location":"202_Gouges (40p)","Summary":"Couches minces et techniques de microfabrication CM01"},{"Start":"20251024T140000","End":"20251024T170000","StartDate":{"Year":"2025","Month":"10","Day":"24","Hour":"14","Minute":"00","Seconde":"00"},"EndDate":{"Year":"2025","Month":"10","Day":"24","Hour":"17","Minute":"00","Seconde":"00"},"Location":"265_Gouges (30p),266_Gouges_30,202_Gouges_40,203_Gouges_40","Summary":"Anglais pour ingenieur 1ere annee TD01"},{"Start":"20251103T083000","End":"20251103T103000","StartDate":{"Year":"2025","Month":"11","Day":"03","Hour":"08","Minute":"30","Seconde":"00"},"EndDate":{"Year":"2025","Month":"11","Day":"03","Hour":"10","Minute":"30","Seconde":"00"},"Location":"202_Gouges (40p)","Summary":"Theorie de Lie, representations et geometrie II CM01"},{"Start":"20251103T104500","End":"20251103T124500","StartDate":{"Year":"2025","Month":"11","Day":"03","Hour":"10","Minute":"45","Seconde":"00"},"EndDate":{"Year":"2025","Month":"11","Day":"03","Hour":"12","Minute":"45","Seconde":"00"},"Location":"202_Gouges (40p)","Summary":"Surfaces et interfaces TD01"},{"Start":"20251103T140000","End":"20251103T160000","StartDate":{"Year":"2025","Month":"11","Day":"03","Hour":"14","Minute":"00","Seconde":"00"},"EndDate":{"Year":"2025","Month":"11","Day":"03","Hour":"16","Minute":"00","Seconde":"00"},"Location":"202_Gouges (40p)","Summary":"Projet professionnel (FISE) - TD"},{"Start":"20251103T160000","End":"20251103T180000","StartDate":{"Year":"2025","Month":"11","Day":"03","Hour":"16","Minute":"00","Seconde":"00"},"EndDate":{"Year":"2025","Month":"11","Day":"03","Hour":"18","Minute":"00","Seconde":"00"},"Location":"202_Gouges (40p)","Summary":"Systemes de telecommunications 1 TD01"},{"Start":"20251104T090000","End":"20251104T120000","StartDate":{"Year":"2025","Month":"11","Day":"04","Hour":"09","Minute":"00","Seconde":"00"},"EndDate":{"Year":"2025","Month":"11","Day":"04","Hour":"12","Minute":"00","Seconde":"00"},"Location":"202_Gouges (40p),203_Gouges_40,265_Gouges_30,266_Gouges_30","Summary":"Anglais pour ingenieur 2eme annee TD01"},{"Start":"20251104T130000","End":"20251104T150000","StartDate":{"Year":"2025","Month":"11","Day":"04","Hour":"13","Minute":"00","Seconde":"00"},"EndDate":{"Year":"2025","Month":"11","Day":"04","Hour":"15","Minute":"00","Seconde":"00"},"Location":"202_Gouges (40p)","Summary":"MANAGEMENT PROJET GR 4"},{"Start":"20251104T151500","End":"20251104T181500","StartDate":{"Year":"2025","Month":"11","Day":"04","Hour":"15","Minute":"15","Seconde":"00"},"EndDate":{"Year":"2025","Month":"11","Day":"04","Hour":"18","Minute":"15","Seconde":"00"},"Location":"202_Gouges (40p)","Summary":"Animation d'equipe Gr 3"},{"Start":"20251105T083000","End":"20251105T100000","StartDate":{"Year":"2025","Month":"11","Day":"05","Hour":"08","Minute":"30","Seconde":"00"},"EndDate":{"Year":"2025","Month":"11","Day":"05","Hour":"10","Minute":"00","Seconde":"00"},"Location":"202_Gouges (40p)","Summary":"INFORMATIQUE FONDAMENTALE CM"},{"Start":"20251105T103000","End":"20251105T120000","StartDate":{"Year":"2025","Month":"11","Day":"05","Hour":"10","Minute":"30","Seconde":"00"},"EndDate":{"Year":"2025","Month":"11","Day":"05","Hour":"12","Minute":"00","Seconde":"00"},"Location":"202_Gouges (40p)","Summary":"INFORMATIQUE FONDAMENTALE CM"},{"Start":"20251105T140000","End":"20251105T170000","StartDate":{"Year":"2025","Month":"11","Day":"05","Hour":"14","Minute":"00","Seconde":"00"},"EndDate":{"Year":"2025","Month":"11","Day":"05","Hour":"17","Minute":"00","Seconde":"00"},"Location":"202_Gouges (40p),255_Gouges_60,203_Gouges_40,266_Gouges_30","Summary":"Anglais"},{"Start":"20251106T083000","End":"20251106T103000","StartDate":{"Year":"2025","Month":"11","Day":"06","Hour":"08","Minute":"30","Seconde":"00"},"EndDate":{"Year":"2025","Month":"11","Day":"06","Hour":"10","Minute":"30","Seconde":"00"},"Location":"202_Gouges (40p)","Summary":"Algebre et Analyse 3 TD03"},{"Start":"20251106T104500","End":"20251106T124500","StartDate":{"Year":"2025","Month":"11","Day":"06","Hour":"10","Minute":"45","Seconde":"00"},"EndDate":{"Year":"2025","Month":"11","Day":"06","Hour":"12","Minute":"45","Seconde":"00"},"Location":"202_Gouges (40p)","Summary":"Mathematiques 1 Gr B"},{"Start":"20251106T141500","End":"20251106T154500","StartDate":{"Year":"2025","Month":"11","Day":"06","Hour":"14","Minute":"15","Seconde":"00"},"EndDate":{"Year":"2025","Month":"11","Day":"06","Hour":"15","Minute":"45","Seconde":"00"},"Location":"202_Gouges (40p)","Summary":"La croissance economique : Faits et theories TD 02"},{"Start":"20251106T160000","End":"20251106T173000","StartDate":{"Year":"2025","Month":"11","Day":"06","Hour":"16","Minute":"00","Seconde":"00"},"EndDate":{"Year":"2025","Month":"11","Day":"06","Hour":"17","Minute":"30","Seconde":"00"},"Location":"202_Gouges (40p)","Summary":"La croissance economique : Faits et theories TD 01"},{"Start":"20251107T090000","End":"20251107T120000","StartDate":{"Year":"2025","Month":"11","Day":"07","Hour":"09","Minute":"00","Seconde":"00"},"EndDate":{"Year":"2025","Month":"11","Day":"07","Hour":"12","Minute":"00","Seconde":"00"},"Location":"202_Gouges (40p)","Summary":"Couches minces et techniques de microfabrication CM01"},{"Start":"20251107T124500","End":"20251107T134500","StartDate":{"Year":"2025","Month":"11","Day":"07","Hour":"12","Minute":"45","Seconde":"00"},"EndDate":{"Year":"2025","Month":"11","Day":"07","Hour":"13","Minute":"45","Seconde":"00"},"Location":"202_Gouges (40p)","Summary":"FRANCAIS 1A TD"},{"Start":"20251107T140000","End":"20251107T170000","StartDate":{"Year":"2025","Month":"11","Day":"07","Hour":"14","Minute":"00","Seconde":"00"},"EndDate":{"Year":"2025","Month":"11","Day":"07","Hour":"17","Minute":"00","Seconde":"00"},"Location":"202_Gouges (40p),265_Gouges_30,203_Gouges_40,266_Gouges_30","Summary":"Anglais pour ingenieur 1ere annee TD01"},{"Start":"20251110T140000","End":"20251110T160000","StartDate":{"Year":"2025","Month":"11","Day":"10","Hour":"14","Minute":"00","Seconde":"00"},"EndDate":{"Year":"2025","Month":"11","Day":"10","Hour":"16","Minute":"00","Seconde":"00"},"Location":"202_Gouges (40p)","Summary":"AUTOMATIQUE CM01"},{"Start":"20251112T083000","End":"20251112T100000","StartDate":{"Year":"2025","Month":"11","Day":"12","Hour":"08","Minute":"30","Seconde":"00"},"EndDate":{"Year":"2025","Month":"11","Day":"12","Hour":"10","Minute":"00","Seconde":"00"},"Location":"202_Gouges (40p)","Summary":"INFORMATIQUE FONDAMENTALE CM"},{"Start":"20251112T103000","End":"20251112T120000","StartDate":{"Year":"2025","Month":"11","Day":"12","Hour":"10","Minute":"30","Seconde":"00"},"EndDate":{"Year":"2025","Month":"11","Day":"12","Hour":"12","Minute":"00","Seconde":"00"},"Location":"202_Gouges (40p)","Summary":"INFORMATIQUE FONDAMENTALE CM"},{"Start":"20251112T120000","End":"20251112T140000","StartDate":{"Year":"2025","Month":"11","Day":"12","Hour":"12","Minute":"00","Seconde":"00"},"EndDate":{"Year":"2025","Month":"11","Day":"12","Hour":"14","Minute":"00","Seconde":"00"},"Location":"202_Gouges (40p)","Summary":"Scrabble"},{"Start":"20251112T140000","End":"20251112T170000","StartDate":{"Year":"2025","Month":"11","Day":"12","Hour":"14","Minute":"00","Seconde":"00"},"EndDate":{"Year":"2025","Month":"11","Day":"12","Hour":"17","Minute":"00","Seconde":"00"},"Location":"202_Gouges (40p),255_Gouges_60,203_Gouges_40,266_Gouges_30","Summary":"Anglais"},{"Start":"20251113T083000","End":"20251113T103000","StartDate":{"Year":"2025","Month":"11","Day":"13","Hour":"08","Minute":"30","Seconde":"00"},"EndDate":{"Year":"2025","Month":"11","Day":"13","Hour":"10","Minute":"30","Seconde":"00"},"Location":"202_Gouges (40p)","Summary":"Algebre et Analyse 3 TD03"},{"Start":"20251113T104500","End":"20251113T124500","StartDate":{"Year":"2025","Month":"11","Day":"13","Hour":"10","Minute":"45","Seconde":"00"},"EndDate":{"Year":"2025","Month":"11","Day":"13","Hour":"12","Minute":"45","Seconde":"00"},"Location":"202_Gouges (40p)","Summary":"Mathematiques 1 Gr B"},{"Start":"20251113T141500","End":"20251113T154500","StartDate":{"Year":"2025","Month":"11","Day":"13","Hour":"14","Minute":"15","Seconde":"00"},"EndDate":{"Year":"2025","Month":"11","Day":"13","Hour":"15","Minute":"45","Seconde":"00"},"Location":"202_Gouges (40p)","Summary":"La croissance economique : Faits et theories TD 02"},{"Start":"20251113T160000","End":"20251113T173000","StartDate":{"Year":"2025","Month":"11","Day":"13","Hour":"16","Minute":"00","Seconde":"00"},"EndDate":{"Year":"2025","Month":"11","Day":"13","Hour":"17","Minute":"30","Seconde":"00"},"Location":"202_Gouges (40p)","Summary":"La croissance economique : Faits et theories TD 01"},{"Start":"20251114T090000","End":"20251114T120000","StartDate":{"Year":"2025","Month":"11","Day":"14","Hour":"09","Minute":"00","Seconde":"00"},"EndDate":{"Year":"2025","Month":"11","Day":"14","Hour":"12","Minute":"00","Seconde":"00"},"Location":"202_Gouges (40p)","Summary":"Couches minces et techniques de microfabrication CM01"},{"Start":"20251114T124500","End":"20251114T134500","StartDate":{"Year":"2025","Month":"11","Day":"14","Hour":"12","Minute":"45","Seconde":"00"},"EndDate":{"Year":"2025","Month":"11","Day":"14","Hour":"13","Minute":"45","Seconde":"00"},"Location":"202_Gouges (40p)","Summary":"FRANCAIS 1A TD"},{"Start":"20251114T140000","End":"20251114T170000","StartDate":{"Year":"2025","Month":"11","Day":"14","Hour":"14","Minute":"00","Seconde":"00"},"EndDate":{"Year":"2025","Month":"11","Day":"14","Hour":"17","Minute":"00","Seconde":"00"},"Location":"202_Gouges (40p),265_Gouges_30,203_Gouges_40,266_Gouges_30","Summary":"Anglais pour ingenieur 1ere annee TD01"},{"Start":"20251117T083000","End":"20251117T123000","StartDate":{"Year":"2025","Month":"11","Day":"17","Hour":"08","Minute":"30","Seconde":"00"},"EndDate":{"Year":"2025","Month":"11","Day":"17","Hour":"12","Minute":"30","Seconde":"00"},"Location":"202_Gouges (40p)","Summary":"Ecotoxicologie (EcoTox) CM01"},{"Start":"20251117T140000","End":"20251117T160000","StartDate":{"Year":"2025","Month":"11","Day":"17","Hour":"14","Minute":"00","Seconde":"00"},"EndDate":{"Year":"2025","Month":"11","Day":"17","Hour":"16","Minute":"00","Seconde":"00"},"Location":"202_Gouges (40p)","Summary":"Projet professionnel (FISE) - TD"},{"Start":"20251117T160000","End":"20251117T180000","StartDate":{"Year":"2025","Month":"11","Day":"17","Hour":"16","Minute":"00","Seconde":"00"},"EndDate":{"Year":"2025","Month":"11","Day":"17","Hour":"18","Minute":"00","Seconde":"00"},"Location":"202_Gouges (40p)","Summary":"Systemes de telecommunications 1 TD01"},{"Start":"20251118T090000","End":"20251118T120000","StartDate":{"Year":"2025","Month":"11","Day":"18","Hour":"09","Minute":"00","Seconde":"00"},"EndDate":{"Year":"2025","Month":"11","Day":"18","Hour":"12","Minute":"00","Seconde":"00"},"Location":"202_Gouges (40p),203_Gouges_40,265_Gouges_30,266_Gouges_30","Summary":"Anglais pour ingenieur 2eme annee TD01"},{"Start":"20251118T140000","End":"20251118T160000","StartDate":{"Year":"2025","Month":"11","Day":"18","Hour":"14","Minute":"00","Seconde":"00"},"EndDate":{"Year":"2025","Month":"11","Day":"18","Hour":"16","Minute":"00","Seconde":"00"},"Location":"202_Gouges (40p)","Summary":"L'IA appliquee a la chimie des materiaux CM01"},{"Start":"20251119T083000","End":"20251119T100000","StartDate":{"Year":"2025","Month":"11","Day":"19","Hour":"08","Minute":"30","Seconde":"00"},"EndDate":{"Year":"2025","Month":"11","Day":"19","Hour":"10","Minute":"00","Seconde":"00"},"Location":"202_Gouges (40p)","Summary":"INFORMATIQUE FONDAMENTALE CM"},{"Start":"20251119T103000","End":"20251119T120000","StartDate":{"Year":"2025","Month":"11","Day":"19","Hour":"10","Minute":"30","Seconde":"00"},"EndDate":{"Year":"2025","Month":"11","Day":"19","Hour":"12","Minute":"00","Seconde":"00"},"Location":"202_Gouges (40p)","Summary":"INFORMATIQUE FONDAMENTALE CM"},{"Start":"20251119T120000","End":"20251119T140000","StartDate":{"Year":"2025","Month":"11","Day":"19","Hour":"12","Minute":"00","Seconde":"00"},"EndDate":{"Year":"2025","Month":"11","Day":"19","Hour":"14","Minute":"00","Seconde":"00"},"Location":"202_Gouges (40p)","Summary":"Scrabble"},{"Start":"20251119T140000","End":"20251119T170000","StartDate":{"Year":"2025","Month":"11","Day":"19","Hour":"14","Minute":"00","Seconde":"00"},"EndDate":{"Year":"2025","Month":"11","Day":"19","Hour":"17","Minute":"00","Seconde":"00"},"Location":"202_Gouges (40p),255_Gouges_60,203_Gouges_40,266_Gouges_30","Summary":"Anglais"},{"Start":"20251120T083000","End":"20251120T103000","StartDate":{"Year":"2025","Month":"11","Day":"20","Hour":"08","Minute":"30","Seconde":"00"},"EndDate":{"Year":"2025","Month":"11","Day":"20","Hour":"10","Minute":"30","Seconde":"00"},"Location":"202_Gouges (40p)","Summary":"BASES DE DONNEES CM01"},{"Start":"20251120T104500","End":"20251120T124500","StartDate":{"Year":"2025","Month":"11","Day":"20","Hour":"10","Minute":"45","Seconde":"00"},"EndDate":{"Year":"2025","Month":"11","Day":"20","Hour":"12","Minute":"45","Seconde":"00"},"Location":"202_Gouges (40p)","Summary":"Mathematiques 1 Gr B"},{"Start":"20251120T141500","End":"20251120T154500","StartDate":{"Year":"2025","Month":"11","Day":"20","Hour":"14","Minute":"15","Seconde":"00"},"EndDate":{"Year":"2025","Month":"11","Day":"20","Hour":"15","Minute":"45","Seconde":"00"},"Location":"202_Gouges (40p)","Summary":"La croissance economique : Faits et theories TD 02"},{"Start":"20251120T160000","End":"20251120T173000","StartDate":{"Year":"2025","Month":"11","Day":"20","Hour":"16","Minute":"00","Seconde":"00"},"EndDate":{"Year":"2025","Month":"11","Day":"20","Hour":"17","Minute":"30","Seconde":"00"},"Location":"202_Gouges (40p)","Summary":"La croissance economique : Faits et theories TD 01"},{"Start":"20251121T090000","End":"20251121T120000","StartDate":{"Year":"2025","Month":"11","Day":"21","Hour":"09","Minute":"00","Seconde":"00"},"EndDate":{"Year":"2025","Month":"11","Day":"21","Hour":"12","Minute":"00","Seconde":"00"},"Location":"202_Gouges (40p)","Summary":"Couches minces et techniques de microfabrication CM01"},{"Start":"20251121T124500","End":"20251121T134500","StartDate":{"Year":"2025","Month":"11","Day":"21","Hour":"12","Minute":"45","Seconde":"00"},"EndDate":{"Year":"2025","Month":"11","Day":"21","Hour":"13","Minute":"45","Seconde":"00"},"Location":"202_Gouges (40p)","Summary":"FRANCAIS 1A TD"},{"Start":"20251121T140000","End":"20251121T170000","StartDate":{"Year":"2025","Month":"11","Day":"21","Hour":"14","Minute":"00","Seconde":"00"},"EndDate":{"Year":"2025","Month":"11","Day":"21","Hour":"17","Minute":"00","Seconde":"00"},"Location":"202_Gouges (40p),265_Gouges_30,203_Gouges_40,266_Gouges_30","Summary":"Anglais pour ingenieur 1ere annee TD01"},{"Start":"20251124T104500","End":"20251124T124500","StartDate":{"Year":"2025","Month":"11","Day":"24","Hour":"10","Minute":"45","Seconde":"00"},"EndDate":{"Year":"2025","Month":"11","Day":"24","Hour":"12","Minute":"45","Seconde":"00"},"Location":"202_Gouges (40p)","Summary":"Surfaces et interfaces TD01"},{"Start":"20251124T140000","End":"20251124T160000","StartDate":{"Year":"2025","Month":"11","Day":"24","Hour":"14","Minute":"00","Seconde":"00"},"EndDate":{"Year":"2025","Month":"11","Day":"24","Hour":"16","Minute":"00","Seconde":"00"},"Location":"202_Gouges (40p)","Summary":"Systemes de telecommunications 1 CM01"},{"Start":"20251124T160000","End":"20251124T180000","StartDate":{"Year":"2025","Month":"11","Day":"24","Hour":"16","Minute":"00","Seconde":"00"},"EndDate":{"Year":"2025","Month":"11","Day":"24","Hour":"18","Minute":"00","Seconde":"00"},"Location":"202_Gouges (40p)","Summary":"Systemes de telecommunications 1 TD01"},{"Start":"20251125T090000","End":"20251125T120000","StartDate":{"Year":"2025","Month":"11","Day":"25","Hour":"09","Minute":"00","Seconde":"00"},"EndDate":{"Year":"2025","Month":"11","Day":"25","Hour":"12","Minute":"00","Seconde":"00"},"Location":"202_Gouges (40p),203_Gouges_40,265_Gouges_30,266_Gouges_30","Summary":"Anglais pour ingenieur 2eme annee TD01"},{"Start":"20251125T121500","End":"20251125T141500","StartDate":{"Year":"2025","Month":"11","Day":"25","Hour":"12","Minute":"15","Seconde":"00"},"EndDate":{"Year":"2025","Month":"11","Day":"25","Hour":"14","Minute":"15","Seconde":"00"},"Location":"202_Gouges (40p)","Summary":"créneau jeremy"},{"Start":"20251126T083000","End":"20251126T100000","StartDate":{"Year":"2025","Month":"11","Day":"26","Hour":"08","Minute":"30","Seconde":"00"},"EndDate":{"Year":"2025","Month":"11","Day":"26","Hour":"10","Minute":"00","Seconde":"00"},"Location":"202_Gouges (40p)","Summary":"INFORMATIQUE FONDAMENTALE CM"},{"Start":"20251126T103000","End":"20251126T120000","StartDate":{"Year":"2025","Month":"11","Day":"26","Hour":"10","Minute":"30","Seconde":"00"},"EndDate":{"Year":"2025","Month":"11","Day":"26","Hour":"12","Minute":"00","Seconde":"00"},"Location":"202_Gouges (40p)","Summary":"INFORMATIQUE FONDAMENTALE CM"},{"Start":"20251126T120000","End":"20251126T140000","StartDate":{"Year":"2025","Month":"11","Day":"26","Hour":"12","Minute":"00","Seconde":"00"},"EndDate":{"Year":"2025","Month":"11","Day":"26","Hour":"14","Minute":"00","Seconde":"00"},"Location":"202_Gouges (40p)","Summary":"Scrabble"},{"Start":"20251126T140000","End":"20251126T170000","StartDate":{"Year":"2025","Month":"11","Day":"26","Hour":"14","Minute":"00","Seconde":"00"},"EndDate":{"Year":"2025","Month":"11","Day":"26","Hour":"17","Minute":"00","Seconde":"00"},"Location":"202_Gouges (40p),255_Gouges_60,203_Gouges_40,266_Gouges_30","Summary":"Anglais"},{"Start":"20251127T083000","End":"20251127T103000","StartDate":{"Year":"2025","Month":"11","Day":"27","Hour":"08","Minute":"30","Seconde":"00"},"EndDate":{"Year":"2025","Month":"11","Day":"27","Hour":"10","Minute":"30","Seconde":"00"},"Location":"202_Gouges (40p)","Summary":"Tech Repair TD03"},{"Start":"20251127T104500","End":"20251127T124500","StartDate":{"Year":"2025","Month":"11","Day":"27","Hour":"10","Minute":"45","Seconde":"00"},"EndDate":{"Year":"2025","Month":"11","Day":"27","Hour":"12","Minute":"45","Seconde":"00"},"Location":"202_Gouges (40p)","Summary":"Mathematiques 1 Gr B"},{"Start":"20251127T141500","End":"20251127T154500","StartDate":{"Year":"2025","Month":"11","Day":"27","Hour":"14","Minute":"15","Seconde":"00"},"EndDate":{"Year":"2025","Month":"11","Day":"27","Hour":"15","Minute":"45","Seconde":"00"},"Location":"202_Gouges (40p)","Summary":"La croissance economique : Faits et theories TD 02"},{"Start":"20251127T160000","End":"20251127T173000","StartDate":{"Year":"2025","Month":"11","Day":"27","Hour":"16","Minute":"00","Seconde":"00"},"EndDate":{"Year":"2025","Month":"11","Day":"27","Hour":"17","Minute":"30","Seconde":"00"},"Location":"202_Gouges (40p)","Summary":"La croissance economique : Faits et theories TD 01"},{"Start":"20251128T090000","End":"20251128T120000","StartDate":{"Year":"2025","Month":"11","Day":"28","Hour":"09","Minute":"00","Seconde":"00"},"EndDate":{"Year":"2025","Month":"11","Day":"28","Hour":"12","Minute":"00","Seconde":"00"},"Location":"202_Gouges (40p)","Summary":"Couches minces et techniques de microfabrication CM01"},{"Start":"20251128T124500","End":"20251128T134500","StartDate":{"Year":"2025","Month":"11","Day":"28","Hour":"12","Minute":"45","Seconde":"00"},"EndDate":{"Year":"2025","Month":"11","Day":"28","Hour":"13","Minute":"45","Seconde":"00"},"Location":"202_Gouges (40p)","Summary":"FRANCAIS 1A TD"},{"Start":"20251128T140000","End":"20251128T170000","StartDate":{"Year":"2025","Month":"11","Day":"28","Hour":"14","Minute":"00","Seconde":"00"},"EndDate":{"Year":"2025","Month":"11","Day":"28","Hour":"17","Minute":"00","Seconde":"00"},"Location":"202_Gouges (40p),265_Gouges_30,203_Gouges_40,266_Gouges_30","Summary":"Anglais pour ingenieur 1ere annee TD01"},{"Start":"20251201T083000","End":"20251201T103000","StartDate":{"Year":"2025","Month":"12","Day":"01","Hour":"08","Minute":"30","Seconde":"00"},"EndDate":{"Year":"2025","Month":"12","Day":"01","Hour":"10","Minute":"30","Seconde":"00"},"Location":"202_Gouges (40p)","Summary":"Theorie de Lie, representations et geometrie II CM01"},{"Start":"20251201T140000","End":"20251201T160000","StartDate":{"Year":"2025","Month":"12","Day":"01","Hour":"14","Minute":"00","Seconde":"00"},"EndDate":{"Year":"2025","Month":"12","Day":"01","Hour":"16","Minute":"00","Seconde":"00"},"Location":"202_Gouges (40p)","Summary":"Projet professionnel (FISE) - TD"},{"Start":"20251202T090000","End":"20251202T120000","StartDate":{"Year":"2025","Month":"12","Day":"02","Hour":"09","Minute":"00","Seconde":"00"},"EndDate":{"Year":"2025","Month":"12","Day":"02","Hour":"12","Minute":"00","Seconde":"00"},"Location":"202_Gouges (40p),203_Gouges_40,265_Gouges_30,266_Gouges_30","Summary":"Anglais pour ingenieur 2eme annee TD01"},{"Start":"20251202T130000","End":"20251202T150000","StartDate":{"Year":"2025","Month":"12","Day":"02","Hour":"13","Minute":"00","Seconde":"00"},"EndDate":{"Year":"2025","Month":"12","Day":"02","Hour":"15","Minute":"00","Seconde":"00"},"Location":"202_Gouges (40p)","Summary":"NOTIONS DE SYSTEMES ET ANALYSE SYSTEMES Gr C"},{"Start":"20251202T151500","End":"20251202T181500","StartDate":{"Year":"2025","Month":"12","Day":"02","Hour":"15","Minute":"15","Seconde":"00"},"EndDate":{"Year":"2025","Month":"12","Day":"02","Hour":"18","Minute":"15","Seconde":"00"},"Location":"202_Gouges (40p)","Summary":"Animation d'equipe Gr 3"},{"Start":"20251203T083000","End":"20251203T100000","StartDate":{"Year":"2025","Month":"12","Day":"03","Hour":"08","Minute":"30","Seconde":"00"},"EndDate":{"Year":"2025","Month":"12","Day":"03","Hour":"10","Minute":"00","Seconde":"00"},"Location":"202_Gouges (40p)","Summary":"INFORMATIQUE FONDAMENTALE CM"},{"Start":"20251203T103000","End":"20251203T120000","StartDate":{"Year":"2025","Month":"12","Day":"03","Hour":"10","Minute":"30","Seconde":"00"},"EndDate":{"Year":"2025","Month":"12","Day":"03","Hour":"12","Minute":"00","Seconde":"00"},"Location":"202_Gouges (40p)","Summary":"INFORMATIQUE FONDAMENTALE CM"},{"Start":"20251203T120000","End":"20251203T140000","StartDate":{"Year":"2025","Month":"12","Day":"03","Hour":"12","Minute":"00","Seconde":"00"},"EndDate":{"Year":"2025","Month":"12","Day":"03","Hour":"14","Minute":"00","Seconde":"00"},"Location":"202_Gouges (40p)","Summary":"Scrabble"},{"Start":"20251203T140000","End":"20251203T170000","StartDate":{"Year":"2025","Month":"12","Day":"03","Hour":"14","Minute":"00","Seconde":"00"},"EndDate":{"Year":"2025","Month":"12","Day":"03","Hour":"17","Minute":"00","Seconde":"00"},"Location":"202_Gouges (40p),255_Gouges_60,203_Gouges_40,266_Gouges_30","Summary":"Anglais"},{"Start":"20251204T090000","End":"20251204T103000","StartDate":{"Year":"2025","Month":"12","Day":"04","Hour":"09","Minute":"00","Seconde":"00"},"EndDate":{"Year":"2025","Month":"12","Day":"04","Hour":"10","Minute":"30","Seconde":"00"},"Location":"202_Gouges (40p)","Summary":"Tech Repair TD03"},{"Start":"20251204T104500","End":"20251204T124500","StartDate":{"Year":"2025","Month":"12","Day":"04","Hour":"10","Minute":"45","Seconde":"00"},"EndDate":{"Year":"2025","Month":"12","Day":"04","Hour":"12","Minute":"45","Seconde":"00"},"Location":"202_Gouges (40p)","Summary":"Mathematiques 1 Gr B"},{"Start":"20251204T141500","End":"20251204T154500","StartDate":{"Year":"2025","Month":"12","Day":"04","Hour":"14","Minute":"15","Seconde":"00"},"EndDate":{"Year":"2025","Month":"12","Day":"04","Hour":"15","Minute":"45","Seconde":"00"},"Location":"202_Gouges (40p)","Summary":"La croissance economique : Faits et theories TD 02"},{"Start":"20251204T160000","End":"20251204T173000","StartDate":{"Year":"2025","Month":"12","Day":"04","Hour":"16","Minute":"00","Seconde":"00"},"EndDate":{"Year":"2025","Month":"12","Day":"04","Hour":"17","Minute":"30","Seconde":"00"},"Location":"202_Gouges (40p)","Summary":"La croissance economique : Faits et theories TD 01"},{"Start":"20251205T090000","End":"20251205T120000","StartDate":{"Year":"2025","Month":"12","Day":"05","Hour":"09","Minute":"00","Seconde":"00"},"EndDate":{"Year":"2025","Month":"12","Day":"05","Hour":"12","Minute":"00","Seconde":"00"},"Location":"202_Gouges (40p)","Summary":"Couches minces et techniques de microfabrication CM01"},{"Start":"20251205T140000","End":"20251205T170000","StartDate":{"Year":"2025","Month":"12","Day":"05","Hour":"14","Minute":"00","Seconde":"00"},"EndDate":{"Year":"2025","Month":"12","Day":"05","Hour":"17","Minute":"00","Seconde":"00"},"Location":"202_Gouges (40p)","Summary":"Découvertes Psychanalyse Freudienne APM"},{"Start":"20251208T140000","End":"20251208T160000","StartDate":{"Year":"2025","Month":"12","Day":"08","Hour":"14","Minute":"00","Seconde":"00"},"EndDate":{"Year":"2025","Month":"12","Day":"08","Hour":"16","Minute":"00","Seconde":"00"},"Location":"202_Gouges (40p)","Summary":"Systemes de telecommunications 1 CM01"},{"Start":"20251208T160000","End":"20251208T180000","StartDate":{"Year":"2025","Month":"12","Day":"08","Hour":"16","Minute":"00","Seconde":"00"},"EndDate":{"Year":"2025","Month":"12","Day":"08","Hour":"18","Minute":"00","Seconde":"00"},"Location":"202_Gouges (40p)","Summary":"Systemes de telecommunications 1 TD01"},{"Start":"20251209T151500","End":"20251209T181500","StartDate":{"Year":"2025","Month":"12","Day":"09","Hour":"15","Minute":"15","Seconde":"00"},"EndDate":{"Year":"2025","Month":"12","Day":"09","Hour":"18","Minute":"15","Seconde":"00"},"Location":"202_Gouges (40p)","Summary":"Animation d'equipe Gr 1"},{"Start":"20251210T083000","End":"20251210T130000","StartDate":{"Year":"2025","Month":"12","Day":"10","Hour":"08","Minute":"30","Seconde":"00"},"EndDate":{"Year":"2025","Month":"12","Day":"10","Hour":"13","Minute":"00","Seconde":"00"},"Location":"202_Gouges (40p)","Summary":"INFORMATIQUE FONDAMENTALE CM"},{"Start":"20251211T104500","End":"20251211T124500","StartDate":{"Year":"2025","Month":"12","Day":"11","Hour":"10","Minute":"45","Seconde":"00"},"EndDate":{"Year":"2025","Month":"12","Day":"11","Hour":"12","Minute":"45","Seconde":"00"},"Location":"202_Gouges (40p)","Summary":"Mathematiques 1 Gr B"},{"Start":"20251211T141500","End":"20251211T154500","StartDate":{"Year":"2025","Month":"12","Day":"11","Hour":"14","Minute":"15","Seconde":"00"},"EndDate":{"Year":"2025","Month":"12","Day":"11","Hour":"15","Minute":"45","Seconde":"00"},"Location":"202_Gouges (40p)","Summary":"La croissance economique : Faits et theories TD 02"},{"Start":"20251211T160000","End":"20251211T173000","StartDate":{"Year":"2025","Month":"12","Day":"11","Hour":"16","Minute":"00","Seconde":"00"},"EndDate":{"Year":"2025","Month":"12","Day":"11","Hour":"17","Minute":"30","Seconde":"00"},"Location":"202_Gouges (40p)","Summary":"La croissance economique : Faits et theories TD 01"},{"Start":"20251212T093000","End":"20251212T123000","StartDate":{"Year":"2025","Month":"12","Day":"12","Hour":"09","Minute":"30","Seconde":"00"},"EndDate":{"Year":"2025","Month":"12","Day":"12","Hour":"12","Minute":"30","Seconde":"00"},"Location":"202_Gouges (40p)","Summary":"Découvertes Psychanalyse Post Freudienne M"},{"Start":"20251212T124500","End":"20251212T134500","StartDate":{"Year":"2025","Month":"12","Day":"12","Hour":"12","Minute":"45","Seconde":"00"},"EndDate":{"Year":"2025","Month":"12","Day":"12","Hour":"13","Minute":"45","Seconde":"00"},"Location":"202_Gouges (40p)","Summary":"FRANCAIS 1A TD"},{"Start":"20251212T140000","End":"20251212T170000","StartDate":{"Year":"2025","Month":"12","Day":"12","Hour":"14","Minute":"00","Seconde":"00"},"EndDate":{"Year":"2025","Month":"12","Day":"12","Hour":"17","Minute":"00","Seconde":"00"},"Location":"202_Gouges (40p),265_Gouges_30,203_Gouges_40,266_Gouges_30","Summary":"Anglais pour ingenieur 1ere annee TD01"},{"Start":"20251215T134500","End":"20251215T184500","StartDate":{"Year":"2025","Month":"12","Day":"15","Hour":"13","Minute":"45","Seconde":"00"},"EndDate":{"Year":"2025","Month":"12","Day":"15","Hour":"18","Minute":"45","Seconde":"00"},"Location":"202_Gouges (40p)","Summary":"Soutenance de thèse Miriam Bovi"},{"Start":"20251216T090000","End":"20251216T120000","StartDate":{"Year":"2025","Month":"12","Day":"16","Hour":"09","Minute":"00","Seconde":"00"},"EndDate":{"Year":"2025","Month":"12","Day":"16","Hour":"12","Minute":"00","Seconde":"00"},"Location":"202_Gouges (40p),203_Gouges_40,265_Gouges_30,266_Gouges_30","Summary":"Anglais pour ingenieur 2eme annee TD01"},{"Start":"20251216T141500","End":"20251216T161500","StartDate":{"Year":"2025","Month":"12","Day":"16","Hour":"14","Minute":"15","Seconde":"00"},"EndDate":{"Year":"2025","Month":"12","Day":"16","Hour":"16","Minute":"15","Seconde":"00"},"Location":"202_Gouges (40p)","Summary":"Atelier d'observation: analyser les relations Interethniques TD01"},{"Start":"20251216T163000","End":"20251216T193000","StartDate":{"Year":"2025","Month":"12","Day":"16","Hour":"16","Minute":"30","Seconde":"00"},"EndDate":{"Year":"2025","Month":"12","Day":"16","Hour":"19","Minute":"30","Seconde":"00"},"Location":"202_Gouges (40p)","Summary":"Approche sociologiques comparees de l'immigration CM01"},{"Start":"20251217T140000","End":"20251217T170000","StartDate":{"Year":"2025","Month":"12","Day":"17","Hour":"14","Minute":"00","Seconde":"00"},"EndDate":{"Year":"2025","Month":"12","Day":"17","Hour":"17","Minute":"00","Seconde":"00"},"Location":"202_Gouges (40p),255_Gouges_60,203_Gouges_40,266_Gouges_30","Summary":"Anglais"},{"Start":"20251218T093000","End":"20251218T123000","StartDate":{"Year":"2025","Month":"12","Day":"18","Hour":"09","Minute":"30","Seconde":"00"},"EndDate":{"Year":"2025","Month":"12","Day":"18","Hour":"12","Minute":"30","Seconde":"00"},"Location":"202_Gouges (40p)","Summary":"Theorie \u0026 methodologies de la recherche clinique CM01"},{"Start":"20251218T141500","End":"20251218T154500","StartDate":{"Year":"2025","Month":"12","Day":"18","Hour":"14","Minute":"15","Seconde":"00"},"EndDate":{"Year":"2025","Month":"12","Day":"18","Hour":"15","Minute":"45","Seconde":"00"},"Location":"202_Gouges (40p)","Summary":"La croissance economique : Faits et theories TD 02"},{"Start":"20251218T160000","End":"20251218T173000","StartDate":{"Year":"2025","Month":"12","Day":"18","Hour":"16","Minute":"00","Seconde":"00"},"EndDate":{"Year":"2025","Month":"12","Day":"18","Hour":"17","Minute":"30","Seconde":"00"},"Location":"202_Gouges (40p)","Summary":"La croissance economique : Faits et theories TD 01"},{"Start":"20251219T093000","End":"20251219T123000","StartDate":{"Year":"2025","Month":"12","Day":"19","Hour":"09","Minute":"30","Seconde":"00"},"EndDate":{"Year":"2025","Month":"12","Day":"19","Hour":"12","Minute":"30","Seconde":"00"},"Location":"202_Gouges (40p)","Summary":"Découvertes Psychanalyse Freudienne"},{"Start":"20251219T140000","End":"20251219T170000","StartDate":{"Year":"2025","Month":"12","Day":"19","Hour":"14","Minute":"00","Seconde":"00"},"EndDate":{"Year":"2025","Month":"12","Day":"19","Hour":"17","Minute":"00","Seconde":"00"},"Location":"202_Gouges (40p)","Summary":"Découvertes Psychanalyse Freudienne"},{"Start":"20260109T093000","End":"20260109T123000","StartDate":{"Year":"2026","Month":"01","Day":"09","Hour":"09","Minute":"30","Seconde":"00"},"EndDate":{"Year":"2026","Month":"01","Day":"09","Hour":"12","Minute":"30","Seconde":"00"},"Location":"202_Gouges (40p)","Summary":"Découvertes Psychanalyse Post Freudienne"},{"Start":"20260109T140000","End":"20260109T170000","StartDate":{"Year":"2026","Month":"01","Day":"09","Hour":"14","Minute":"00","Seconde":"00"},"EndDate":{"Year":"2026","Month":"01","Day":"09","Hour":"17","Minute":"00","Seconde":"00"},"Location":"202_Gouges (40p)","Summary":"Découvertes Psychanalyse Post Freudienne"}]